ynca/__init__.py
ynca/api.py
ynca/connection.py
ynca/constants.py
ynca/converters.py
ynca/debug_server.py
ynca/enums.py
ynca/errors.py
ynca/function.py
ynca/helpers.py
ynca/modelinfo.py
ynca/protocol.py
ynca/py.typed
ynca/subunit.py
ynca/terminal.py
ynca/subunits/__init__.py
ynca/subunits/airplay.py
ynca/subunits/bt.py
ynca/subunits/dab.py
ynca/subunits/deezer.py
ynca/subunits/ipod.py
ynca/subunits/ipodusb.py
ynca/subunits/mclink.py
ynca/subunits/napster.py
ynca/subunits/netradio.py
ynca/subunits/pandora.py
ynca/subunits/pc.py
ynca/subunits/rhap.py
ynca/subunits/server.py
ynca/subunits/sirius.py
ynca/subunits/spotify.py
ynca/subunits/system.py
ynca/subunits/tidal.py
ynca/subunits/tun.py
ynca/subunits/uaw.py
ynca/subunits/usb.py
ynca/subunits/zone.py
ynca-5.29.0.dist-info/licenses/LICENSE.txt
ynca-5.29.0.dist-info/METADATA
ynca-5.29.0.dist-info/WHEEL
ynca-5.29.0.dist-info/top_level.txt
ynca-5.29.0.dist-info/RECORD
