Metadata-Version: 2.4
Name: ynca
Version: 5.29.0
Summary: Package to control Yamaha receivers that support the YNCA protocol.
Author-email: Michel van de Wetering <michel.van.de.wetering+ynca@gmail.com>
License-Expression: MIT
Project-URL: Homepage, https://github.com/mvdwetering/ynca
Classifier: Programming Language :: Python :: 3
Classifier: Operating System :: OS Independent
Classifier: Development Status :: 5 - Production/Stable
Classifier: Intended Audience :: Developers
Classifier: Topic :: Home Automation
Classifier: Topic :: Software Development :: Libraries
Requires-Python: >=3.11
License-File: LICENSE.txt
Requires-Dist: pyserial>=3.4
Provides-Extra: dev
Requires-Dist: mypy==1.15.0; extra == "dev"
Requires-Dist: ruff==0.9.7; extra == "dev"
Requires-Dist: pytest>=7.0.0; extra == "dev"
Requires-Dist: pytest-cov; extra == "dev"
Requires-Dist: pytest-mock; extra == "dev"
Requires-Dist: mock-serial==0.0.1; extra == "dev"
Requires-Dist: black==25.1.0; extra == "dev"
Dynamic: license-file
